CONTRIBUTING.rst
LICENSE
MANIFEST.in
README.rst
setup.cfg
setup.py
pyzerproc/__init__.py
pyzerproc/cli.py
pyzerproc/discovery.py
pyzerproc/exceptions.py
pyzerproc/light.py
pyzerproc.egg-info/PKG-INFO
pyzerproc.egg-info/SOURCES.txt
pyzerproc.egg-info/dependency_links.txt
pyzerproc.egg-info/entry_points.txt
pyzerproc.egg-info/not-zip-safe
pyzerproc.egg-info/requires.txt
pyzerproc.egg-info/top_level.txt
tests/__init__.py
tests/conftest.py
tests/test_discovery.py
tests/test_light.py