Metadata-Version: 2.1
Name: pyzerproc
Version: 0.4.11
Summary: Async library to control Zerproc Bluetooth LED smart string lights
Home-page: https://github.com/emlove/pyzerproc
Author: Emily Love Mills
Author-email: emily@emlove.me
License: Apache Software License 2.0
Keywords: pyzerproc
Platform: UNKNOWN
Classifier: Development Status :: 4 - Beta
Classifier: Intended Audience :: Developers
Classifier: License :: OSI Approved :: Apache Software License
Classifier: Natural Language :: English
Classifier: Programming Language :: Python :: 3
Classifier: Programming Language :: Python :: 3.7
Classifier: Programming Language :: Python :: 3.8
Classifier: Programming Language :: Python :: 3.9
Classifier: Programming Language :: Python :: 3.10
Requires-Python: >=3.6
License-File: LICENSE
